djangoviz/__init__.py
djangoviz/apps.py
djangoviz/management/__init__.py
djangoviz/management/commands/__init__.py
djangoviz/management/commands/djangoviz.py
djangoviz-0.1.1.dist-info/LICENSE
djangoviz-0.1.1.dist-info/METADATA
djangoviz-0.1.1.dist-info/WHEEL
djangoviz-0.1.1.dist-info/top_level.txt
djangoviz-0.1.1.dist-info/RECORD
